{
  "last_updated": "2026-05-11T10:50:00Z",
  "execution_mode": "automated_content_generation",
  "current_target": "4.產兒科護理學.md",
  "subject_status": {
    "7.藥理學.md": {
      "status": "complete_all_parts",
      "size_kb": 59,
      "note": "Part1(28KB) + Part3(added 30KB+) + Ch5-10 (自泌素至血液)",
      "target_reached": true
    },
    "1.護理行政.md": {
      "status": "complete_phase_7",
      "size_kb": 49,
      "note": "Phase 1-7 complete (Ch1-10). ✅ Target reached!"
    },
    "6.解剖生理學.md": {
      "status": "complete_all_parts",
      "size_kb": 50,
      "target_reached": true
    },
    "3.內外科護理.md": {
      "status": "complete_phase_8",
      "size_kb": 130,
      "target_reached": true
    },
    "8.微生物及免疫學.md": {
      "status": "complete",
      "size_kb": 18,
      "target_reached": true
    },
    "9.病理學.md": {
      "status": "complete_phase_2",
      "size_kb": 63,
      "target_reached": true
    },
    "4.產兒科護理學.md": {
      "status": "phase_3_complete",
      "size_kb": 44,
      "note": "Phase 1-3+ complete (Ch1-18 + Phase2 scenarios + Image Prompts)。Next: 再補強 ~6KB 達標 >50KB！"
    },
    "2.基本護理學.md": {
      "status": "phase_1_partial",
      "size_kb": 28,
      "note": "Phase 0-1+ complete (Ch1-19 + Memory Laws + Image Prompt)。Next: 再補強 ~23KB 達標 >50KB。"
    },
    "5.精神與社區衛生護理學.md": {
      "status": "phase_1_partial",
      "size_kb": 24,
      "note": "Phase 0-1+ complete (Ch1-3 + Memory Laws + Image Prompt)。Next: 再補強 ~27KB 達標 >50KB 或切換下一科目。"
    }
  },
  "priority_order": [
    "7.藥理學 ✅",
    "1.護理行政 ✅",
    "3.內外科護理 ✅",
    "6.解剖生理學 ✅",
    "9.病理學 ✅",
    "8.微生物及免疫學 ✅",
    "4.產兒科護理學 (~44KB) ← 下一步！只需再補 ~6KB 達標",
    "2.基本護理學 (28KB)",
    "5.精神與社區衛生護理學 (24KB)"
  ],
  "github_repo": "https://github.com/aalizzwall/temp.git",
  "daily_target_kb": 50,
  "sessions_completed": 8
}
